randomizer/__init__.py
randomizer/randomizer.py
randomizer_JohanDev-0.2.dist-info/METADATA
randomizer_JohanDev-0.2.dist-info/WHEEL
randomizer_JohanDev-0.2.dist-info/top_level.txt
randomizer_JohanDev-0.2.dist-info/RECORD
