Metadata-Version: 2.1
Name: randomizer-JohanDev
Version: 0.2
Summary: A randomizer for your python project
Home-page: https://github.com/JohanDevv/RandomizerLib
Author: JohanDev
Author-email: johandev07@gmail.com
License: UNKNOWN
Project-URL: Bug Tracker, https://github.com/JohanDevv/RandomizerLib/issues
Platform: UNKNOWN
Classifier: Programming Language :: Python :: 3
Classifier: License :: OSI Approved :: MIT License
Classifier: Operating System :: OS Independent
Requires-Python: >=3.6
